kk_scrapy_redis/__init__.py
kk_scrapy_redis/connection.py
kk_scrapy_redis/defaults.py
kk_scrapy_redis/dupefilter.py
kk_scrapy_redis/picklecompat.py
kk_scrapy_redis/pipelines.py
kk_scrapy_redis/queue.py
kk_scrapy_redis/scheduler.py
kk_scrapy_redis/spiders.py
kk_scrapy_redis/stats.py
kk_scrapy_redis/utils.py
kk_scrapy_redis-0.0.1.dist-info/LICENSE
kk_scrapy_redis-0.0.1.dist-info/METADATA
kk_scrapy_redis-0.0.1.dist-info/WHEEL
kk_scrapy_redis-0.0.1.dist-info/top_level.txt
kk_scrapy_redis-0.0.1.dist-info/RECORD
