Metadata-Version: 2.1
Name: kk-scrapy-redis
Version: 0.0.1
Summary: Redis-based components for Scrapy.
Home-page: https://github.com/wgnpj2cg/kk-scrapy-redis
License: MIT
Keywords: kk-scrapy-redis
Classifier: Development Status :: 4 - Beta
Classifier: Intended Audience :: Developers
Classifier: License :: OSI Approved :: MIT License
Classifier: Natural Language :: English
Classifier: Programming Language :: Python :: 3
Classifier: Programming Language :: Python :: 3.7
Classifier: Programming Language :: Python :: 3.8
Classifier: Programming Language :: Python :: 3.9
Classifier: Programming Language :: Python :: 3.10
License-File: LICENSE
Requires-Dist: scrapy (>=2.0)
Requires-Dist: redis (>=4.0)
Requires-Dist: six (>=1.15)
Requires-Dist: coverage
Requires-Dist: flake8
Requires-Dist: mock
Requires-Dist: pytest
Requires-Dist: tox
Requires-Dist: pytest-cov
